{
  "stores": [
    {
      "id": "shopopen",
      "name": "Shop Open",
      "whatsapp": "524491234567",
      "currency": "MXN",
      "logo": "/assets/logos/shopopen.png",
      "active": true
    },
    {
      "id": "onehats",
      "name": "One Hats",
      "whatsapp": "524491234568",
      "currency": "MXN",
      "logo": "/assets/logos/onehats.png",
      "active": true
    },
    {
      "id": "f1",
      "name": "F1 Store",
      "whatsapp": "524491234569",
      "currency": "MXN",
      "logo": "/assets/logos/f1.png",
      "active": true
    },
    {
      "id": "chelispa",
      "name": "Cheli Spa",
      "whatsapp": "524494904451",
      "currency": "MXN",
      "hero": "/assets/heroes/cheli.jpg",
      "plan": "pro",
      "theme": "spa",
      "logo": "/assets/logos/chelispa.png",
      "active": true
    },
       {
      "id": "hernandez-snickers",
      "name": "Hernandez Snickers",
      "whatsapp": "3312436092",
      "currency": "MXN",
      "hero": "/assets/heroes/sneakers.jpg",
      "plan": "pro",
      "logo": "/assets/logos/hdz.jpeg",
      "active": true
    }

  ],

  "products": [

    {
      "id": 1,
      "store": "shopopen",
      "name": "Sudadera Street Negra",
      "price": 720,
      "category": "sudaderas",
      "stock": 10,
      "image": "/assets/products/shopopen/sudadera1.jpg",
      "description": "Sudadera streetwear algodón premium",
      "featured": true,
      "active": true
    },

    {
      "id": 2,
      "store": "shopopen",
      "name": "Sudadera Oversize Blanca",
      "price": 760,
      "category": "sudaderas",
      "stock": 8,
      "image": "/assets/products/shopopen/sudadera2.jpg",
      "description": "Sudadera oversize estilo urbano",
      "featured": false,
      "active": true
    },

    {
      "id": 3,
      "store": "onehats",
      "name": "Gorra Negra Clásica",
      "price": 350,
      "category": "gorras",
      "stock": 12,
      "image": "/assets/products/onehats/gorra1.jpg",
      "description": "Gorra negra clásica ajustable",
      "featured": true,
      "active": true
    },

    {
      "id": 4,
      "store": "onehats",
      "name": "Gorra Blanca Minimal",
      "price": 380,
      "category": "gorras",
      "stock": 9,
      "image": "/assets/products/onehats/gorra2.jpg",
      "description": "Gorra blanca minimalista premium",
      "featured": false,
      "active": true
    },

    {
      "id": 5,
      "store": "f1",
      "name": "Playera Ferrari Racing",
      "price": 650,
      "category": "playeras",
      "stock": 15,
      "image": "/assets/products/f1/ferrari.jpg",
      "description": "Playera Ferrari estilo racing fans",
      "featured": true,
      "active": true
    },

    {
      "id": 6,
      "store": "f1",
      "name": "Playera Red Bull Racing",
      "price": 680,
      "category": "playeras",
      "stock": 13,
      "image": "/assets/products/f1/redbull.jpg",
      "description": "Playera Red Bull Racing edición fans",
      "featured": false,
      "active": true
    },

    {
      "id": 7,
      "store": "chelispa",
      "name": "Kit Facial Hidratante",
      "price": 520,
      "category": "spa",
      "stock": 20,
      "image": "/assets/products/chelispa/facial.jpg",
      "description": "Kit facial hidratante cuidado profesional",
      "featured": true,
      "active": true
    }

  ]
}